gametables.py
gametables-0.1.0.dist-info/LICENSE.txt
gametables-0.1.0.dist-info/METADATA
gametables-0.1.0.dist-info/WHEEL
gametables-0.1.0.dist-info/entry_points.txt
gametables-0.1.0.dist-info/top_level.txt
gametables-0.1.0.dist-info/RECORD
