Metadata-Version: 2.1
Name: gametables
Version: 0.1.0
Summary: Choose random entries from sequences in a YAML file
Home-page: https://github.com/encodis/gametables
Author: Philip Hodder
Author-email: philip.hodder@encodis.com
License: MIT
Keywords: gametables tables games playing
Platform: UNKNOWN
Classifier: License :: OSI Approved :: MIT License
Classifier: Programming Language :: Python :: 3.6
Classifier: Programming Language :: Python :: 3.7
Classifier: Programming Language :: Python :: 3.8
Classifier: Topic :: Games/Entertainment :: Role-Playing
Requires-Dist: pyyaml (>=5.1)
Requires-Dist: py-expression-eval
